moncenterlib/__init__.py
moncenterlib/stream2file.py
moncenterlib/tools.py
moncenterlib/gnss/__init__.py
moncenterlib/gnss/cddis_client.py
moncenterlib/gnss/gnss_time_series.py
moncenterlib/gnss/postprocessing.py
moncenterlib/gnss/quality_check.py
moncenterlib/gnss/rgs_client.py
moncenterlib/gnss/tools.py
moncenterlib/gnss/tools4rnx.py
moncenterlib/gnss/bin/aarch64/anubis_2.3_aarch64_linux
moncenterlib/gnss/bin/aarch64/convbin_2.4.3-34_aarch64_linux
moncenterlib/gnss/bin/aarch64/rnx2rtkp_2.4.3-34_aarch64_linux
moncenterlib/gnss/bin/aarch64/str2str_2.4.3-34_aarch64_linux
moncenterlib/gnss/bin/x86_64/anubis_2.3_x86_64_linux
moncenterlib/gnss/bin/x86_64/convbin_2.4.3-34_x86_64_linux
moncenterlib/gnss/bin/x86_64/rnx2rtkp_2.4.3-34_x86_64_linux
moncenterlib/gnss/bin/x86_64/str2str_2.4.3-34_x86_64_linux
moncenterlib/gnss/conf/estimatetrend.ctl
moncenterlib/gnss/conf/removeoutliers.ctl
moncenterlib/gnss/conf/rnx2rtkp.conf
moncenterlib/tests/__init__.py
moncenterlib/tests/test_stream2file.py
moncenterlib/tests/test_tools.py
moncenterlib/tests/gnss/__init__.py
moncenterlib/tests/gnss/integration_tests/__init__.py
moncenterlib/tests/gnss/integration_tests/test_integration_cddis_client.py
moncenterlib/tests/gnss/integration_tests/test_integration_rgs_client.py
moncenterlib/tests/gnss/unit_tests/__init__.py
moncenterlib/tests/gnss/unit_tests/test_cddis_client.py
moncenterlib/tests/gnss/unit_tests/test_postprocessing.py
moncenterlib/tests/gnss/unit_tests/test_quality_check.py
moncenterlib/tests/gnss/unit_tests/test_rgs_client.py
moncenterlib/tests/gnss/unit_tests/test_tools.py
moncenterlib/tests/gnss/unit_tests/test_tools4rnx.py
moncenterlib-1.0.4.dist-info/METADATA
moncenterlib-1.0.4.dist-info/WHEEL
moncenterlib-1.0.4.dist-info/top_level.txt
moncenterlib-1.0.4.dist-info/RECORD
