Metadata-Version: 2.1
Name: moncenterlib
Version: 1.0.4
Summary: MonCenterLib is a python library for geodetic monitoring. The library contains programs,designed to collect, process, analyze and visualize data for geodetic time series.
Home-page: https://github.com/DanielMamaev/MonCenterLib
Author: Daniel Mamaev
Author-email: moncenter@moncenter.ru
Project-URL: Documentation, https://moncenterlib.readthedocs.io/
Project-URL: Source, https://github.com/DanielMamaev/MonCenterLib
Keywords: python
Classifier: Programming Language :: Python :: 3.10
Classifier: Operating System :: POSIX :: Linux
Requires-Python: >=3.10
Requires-Dist: typeguard ==4.1.5
Requires-Dist: gps-time ==2.8.8
Requires-Dist: requests ==2.31.0
